d_npu_alli/__init__.py
d_npu_alli/client.py
d_npu_alli/test_client.py
d_npu_alli-0.1.0.dist-info/METADATA
d_npu_alli-0.1.0.dist-info/WHEEL
d_npu_alli-0.1.0.dist-info/RECORD
